odoo8_addon_hr_payroll_cancel-8.0.1.0.0.99.dev8-py2.7-nspkg.pth
odoo8_addon_hr_payroll_cancel-8.0.1.0.0.99.dev8.dist-info/METADATA
odoo8_addon_hr_payroll_cancel-8.0.1.0.0.99.dev8.dist-info/RECORD
odoo8_addon_hr_payroll_cancel-8.0.1.0.0.99.dev8.dist-info/WHEEL
odoo8_addon_hr_payroll_cancel-8.0.1.0.0.99.dev8.dist-info/namespace_packages.txt
odoo8_addon_hr_payroll_cancel-8.0.1.0.0.99.dev8.dist-info/top_level.txt
odoo_addons/hr_payroll_cancel/README.rst
odoo_addons/hr_payroll_cancel/__init__.py
odoo_addons/hr_payroll_cancel/__openerp__.py
odoo_addons/hr_payroll_cancel/hooks.py
odoo_addons/hr_payroll_cancel/hr_payslip_view.xml
odoo_addons/hr_payroll_cancel/hr_payslip_workflow.xml
odoo_addons/hr_payroll_cancel/i18n/de.po
odoo_addons/hr_payroll_cancel/i18n/fr.po
odoo_addons/hr_payroll_cancel/i18n/hr_payroll_cancel.pot
odoo_addons/hr_payroll_cancel/i18n/sl.po
odoo_addons/hr_payroll_cancel/static/description/icon.png
